odoo/addons/server_environment_delivery/README.rst
odoo/addons/server_environment_delivery/__init__.py
odoo/addons/server_environment_delivery/__manifest__.py
odoo/addons/server_environment_delivery/i18n/es.po
odoo/addons/server_environment_delivery/i18n/it.po
odoo/addons/server_environment_delivery/i18n/server_environment_delivery.pot
odoo/addons/server_environment_delivery/models/__init__.py
odoo/addons/server_environment_delivery/models/delivery_carrier.py
odoo/addons/server_environment_delivery/readme/CONFIGURE.md
odoo/addons/server_environment_delivery/readme/CONTRIBUTORS.md
odoo/addons/server_environment_delivery/readme/CREDITS.md
odoo/addons/server_environment_delivery/readme/DESCRIPTION.md
odoo/addons/server_environment_delivery/static/description/icon.png
odoo/addons/server_environment_delivery/static/description/index.html
odoo_addon_server_environment_delivery-18.0.1.0.0.3.dist-info/METADATA
odoo_addon_server_environment_delivery-18.0.1.0.0.3.dist-info/WHEEL
odoo_addon_server_environment_delivery-18.0.1.0.0.3.dist-info/top_level.txt
odoo_addon_server_environment_delivery-18.0.1.0.0.3.dist-info/RECORD
