Metadata-Version: 2.1
Name: odoo-addon-server_environment_delivery
Version: 18.0.1.0.0.3
Requires-Python: >=3.10
Requires-Dist: odoo-addon-server_environment==18.0.*
Requires-Dist: odoo==18.0.*
Summary: Configure prod environment for delivery carriers
Home-page: https://github.com/OCA/delivery-carrier
License: AGPL-3
Author: Camptocamp, Odoo Community Association (OCA)
Author-email: support@odoo-community.org
Classifier: Programming Language :: Python
Classifier: Framework :: Odoo
Classifier: Framework :: Odoo :: 18.0
Classifier: License :: OSI Approved :: GNU Affero General Public License v3
Classifier: Development Status :: 3 - Alpha
